KiyatoFN/__init__.py
KiyatoFN-3.0.1.dist-info/METADATA
KiyatoFN-3.0.1.dist-info/WHEEL
KiyatoFN-3.0.1.dist-info/top_level.txt
KiyatoFN-3.0.1.dist-info/RECORD
